[
  {
    "line": "closed-library",
    "scenario": "Multi-sentences",
    "model": "char-match",
    "strictness": "strict",
    "failure_type": "prediction",
    "input": "对你还是欲罢不能，你是我心结，对你我身不由己，言不由衷，口是心非",
    "expected": "，你是我心结",
    "actual": "",
    "accepted": false,
    "confidence": 0.99,
    "reason": "char_match_ambiguous",
    "expected_corrected_context": null,
    "actual_corrected_context": null,
    "source": "1 Thing (Cherokee Remix) - Amerie,Cherokee.lrc",
    "latency_ms": 159.39289999914763
  },
  {
    "line": "closed-library",
    "scenario": "Multi-sentences",
    "model": "char-match",
    "strictness": "strict",
    "failure_type": "prediction",
    "input": "我对你朝思暮想 如今你遥不可及，如此遥不可及，如此遥不可及，如此遥不可及，如此遥不可及",
    "expected": "，噢 挚爱",
    "actual": "",
    "accepted": false,
    "confidence": 0.99,
    "reason": "char_match_ambiguous",
    "expected_corrected_context": null,
    "actual_corrected_context": null,
    "source": "So Far Away - Martin Garrix,David Guetta,Jamie Scott,Romy Dya.lrc",
    "latency_ms": 186.26299999959883
  },
  {
    "line": "closed-library",
    "scenario": "Multi-sentences",
    "model": "char-match",
    "strictness": "strict",
    "failure_type": "prediction",
    "input": "照耀我的房间，我独自坐着，对着月亮倾诉，想与你有所感应，多希望你",
    "expected": "，在另一头",
    "actual": "",
    "accepted": false,
    "confidence": 0.99,
    "reason": "char_match_ambiguous",
    "expected_corrected_context": null,
    "actual_corrected_context": null,
    "source": "Talking to the Moon - Bruno Mars.lrc",
    "latency_ms": 143.54920000005222
  },
  {
    "line": "closed-library",
    "scenario": "Multi-sentences",
    "model": "char-match",
    "strictness": "strict",
    "failure_type": "prediction",
    "input": "也要让 后来人生 精彩着，后来的我们 我期待着，泪水中能看到 你真的 自由了",
    "expected": "，亲爱的",
    "actual": "",
    "accepted": false,
    "confidence": 0.99,
    "reason": "char_match_ambiguous",
    "expected_corrected_context": null,
    "actual_corrected_context": null,
    "source": "后来的我们 - 五月天.lrc",
    "latency_ms": 200.6974000014452
  },
  {
    "line": "closed-library",
    "scenario": "Multi-sentences",
    "model": "char-match",
    "strictness": "strict",
    "failure_type": "prediction",
    "input": "喜欢你没有理由，多想问我们能不能不只是做朋友，能不能出去走走，能不能牵你的手",
    "expected": "，能不能懂我的意思就算不用开口",
    "actual": "",
    "accepted": false,
    "confidence": 0.99,
    "reason": "char_match_ambiguous",
    "expected_corrected_context": null,
    "actual_corrected_context": null,
    "source": "听说我喜欢你 - 老番茄,Bo Peep.lrc",
    "latency_ms": 233.58399999960966
  },
  {
    "line": "closed-library",
    "scenario": "Multi-sentences",
    "model": "char-match",
    "strictness": "strict",
    "failure_type": "prediction",
    "input": "再见一面我可以站得远一点，满天 飞雪 把我心冷却，想问问你最近过得怎么样，有没新的另一半",
    "expected": "，还是和从前一样简单",
    "actual": "",
    "accepted": false,
    "confidence": 0.99,
    "reason": "char_match_ambiguous",
    "expected_corrected_context": null,
    "actual_corrected_context": null,
    "source": "就忘了吧 - 1K.lrc",
    "latency_ms": 250.87100000018836
  },
  {
    "line": "closed-library",
    "scenario": "Multi-sentences",
    "model": "char-match",
    "strictness": "strict",
    "failure_type": "prediction",
    "input": "我睁开双眼 看着空白，忘记你对我的期待，读完了依赖 我很快就，我只能永远读着对白",
    "expected": "，读着我给你的伤害",
    "actual": "",
    "accepted": false,
    "confidence": 0.99,
    "reason": "char_match_ambiguous",
    "expected_corrected_context": null,
    "actual_corrected_context": null,
    "source": "搁浅 - 周杰伦.lrc",
    "latency_ms": 227.1959000008792
  },
  {
    "line": "closed-library",
    "scenario": "Multi-sentences",
    "model": "char-match",
    "strictness": "strict",
    "failure_type": "prediction",
    "input": "内心怅然若失的季节依然在眼前，Stay with me 请来排解我的孤单，唱针跳动，同样的旋律在重复流转",
    "expected": "，我午夜叩响那门玄",
    "actual": "",
    "accepted": false,
    "confidence": 0.99,
    "reason": "char_match_ambiguous",
    "expected_corrected_context": null,
    "actual_corrected_context": null,
    "source": "真夜中のドア～stay with me (Cover) - TOKYO CITYPOP CANDY.lrc",
    "latency_ms": 331.0689000009006
  },
  {
    "line": "closed-library",
    "scenario": "Multi-sentences",
    "model": "char-match",
    "strictness": "strict",
    "failure_type": "prediction",
    "input": "羞答答的玫瑰静悄悄地开，慢慢地绽放她留给我的情怀，春天的手呀翻阅她的等待，我在暗暗思量",
    "expected": "，该不该将她轻轻地摘",
    "actual": "",
    "accepted": false,
    "confidence": 0.99,
    "reason": "char_match_ambiguous",
    "expected_corrected_context": null,
    "actual_corrected_context": null,
    "source": "羞答答的玫瑰静悄悄地开 - 陈之.lrc",
    "latency_ms": 211.67240000067977
  },
  {
    "line": "closed-library",
    "scenario": "Multi-sentences",
    "model": "char-match",
    "strictness": "strict",
    "failure_type": "prediction",
    "input": "今天也过的不太如意，还在慌乱的挣扎中，那份不甘心，令人难为情，流下眼泪",
    "expected": "，我越是陷入其中",
    "actual": "",
    "accepted": false,
    "confidence": 0.99,
    "reason": "char_match_ambiguous",
    "expected_corrected_context": null,
    "actual_corrected_context": null,
    "source": "群青 - YOASOBI.lrc",
    "latency_ms": 143.91950000026554
  },
  {
    "line": "closed-library",
    "scenario": "Multi-sentences",
    "model": "char-match",
    "strictness": "balanced",
    "failure_type": "prediction",
    "input": "我对你朝思暮想 如今你遥不可及，如此遥不可及，如此遥不可及，如此遥不可及，如此遥不可及",
    "expected": "，噢 挚爱",
    "actual": "",
    "accepted": false,
    "confidence": 0.99,
    "reason": "char_match_ambiguous",
    "expected_corrected_context": null,
    "actual_corrected_context": null,
    "source": "So Far Away - Martin Garrix,David Guetta,Jamie Scott,Romy Dya.lrc",
    "latency_ms": 176.4884999993228
  }
]